mfc_scraper/__init__.py
mfc_scraper/__main__.py
mfc_scraper/dumper.py
mfc_scraper/scraper.py
mfc_scraper/locators/__init__.py
mfc_scraper/locators/figure_collection_page_locators.py
mfc_scraper/locators/figure_locators.py
mfc_scraper/locators/figure_page_locators.py
mfc_scraper/pages/__init__.py
mfc_scraper/pages/figure_collection_page.py
mfc_scraper/pages/figure_page.py
mfc_scraper/parsers/__init__.py
mfc_scraper/parsers/figure.py
mfc_scraper/parsers/figure_data.py
mfc_scraper-0.2.0.dist-info/AUTHORS.rst
mfc_scraper-0.2.0.dist-info/LICENSE
mfc_scraper-0.2.0.dist-info/METADATA
mfc_scraper-0.2.0.dist-info/WHEEL
mfc_scraper-0.2.0.dist-info/entry_points.txt
mfc_scraper-0.2.0.dist-info/top_level.txt
mfc_scraper-0.2.0.dist-info/RECORD
